file_tools/__init__.py
file_tools/file.py
file_tools/json_file.py
file_tools/utils/__init__.py
file_tools/utils/functions.py
file_tools-0.1.7.dist-info/LICENSE
file_tools-0.1.7.dist-info/METADATA
file_tools-0.1.7.dist-info/WHEEL
file_tools-0.1.7.dist-info/top_level.txt
file_tools-0.1.7.dist-info/RECORD
