Metadata-Version: 2.1
Name: file-tools
Version: 0.1.7
Summary: File and JSON File Methods.
Home-page: https://github.com/edmundpf/file_tools
Author: Edmund Pfeil
Author-email: edmundpf@buffalo.edu
License: UNKNOWN
Platform: UNKNOWN
Classifier: Programming Language :: Python :: 3
Classifier: License :: OSI Approved :: MIT License
Classifier: Operating System :: OS Independent
